alphacore/__init__.py
alphacore/distributions.py
alphacore/fit_distribution.py
alphacore/fit_linear.py
alphacore/utils.py
alphacore-0.0.8.dist-info/LICENSE
alphacore-0.0.8.dist-info/METADATA
alphacore-0.0.8.dist-info/WHEEL
alphacore-0.0.8.dist-info/top_level.txt
alphacore-0.0.8.dist-info/RECORD
